setup.py
imbolc/__init__.py
imbolc/daemon.py
imbolc/debug.py
imbolc/decorators.py
imbolc/file.py
imbolc/gthread.py
imbolc/kv.py
imbolc/memory.py
imbolc/pp.py
imbolc/send.py
imbolc/structures.py
imbolc/thread.py
imbolc.egg-info/PKG-INFO
imbolc.egg-info/SOURCES.txt
imbolc.egg-info/dependency_links.txt
imbolc.egg-info/requires.txt
imbolc.egg-info/top_level.txt