Metadata-Version: 1.0
Name: imbolc
Version: 0.0.14
Summary: Misc libs
Home-page: http://bitbucket.org/imbolc/imbolc/
Author: Imbolc
Author-email: imbolc@imbolc.name
License: BSD
Platform: UNKNOWN
Classifier: Development Status :: 4 - Beta
Classifier: Intended Audience :: Developers
Classifier: License :: OSI Approved :: BSD License
Classifier: Operating System :: OS Independent
Classifier: Programming Language :: Python
Classifier: Topic :: Software Development :: Libraries :: Python Modules
